jwtee/__init__.py
jwtee/jwtee.py
jwtee-1.0.1.dist-info/licenses/LICENSE
jwtee-1.0.1.dist-info/METADATA
jwtee-1.0.1.dist-info/WHEEL
jwtee-1.0.1.dist-info/entry_points.txt
jwtee-1.0.1.dist-info/top_level.txt
jwtee-1.0.1.dist-info/RECORD
